Workbook

Sheet Dashboard
B2: JET Collaborations — Dashboard de eficiência (CSV de 28/05 como primária)
B4: Período: lançamento dos cupons → 28/05/2026 • Atualização semanal • Resp.: Ruslan Barbolin • Em divergências não-críticas, CSV (mais recente) prevalece sobre Excel (24/05)
B6: Ativações totais | C6: % novos clientes | D6: Corridas (promo) | E6: GMV total (R$) | F6: Receita Cash (R$) | G6: Custo do bônus (R$) | H6: ROI
B7: =Data!G6 | C7: =IFERROR(Data!H6/Data!G6,0) | D7: =Data!J6 | E7: =(Data!N6+Data!P6) | F7: =(Data!O6+Data!Q6) | G7: =((Data!N6+Data!P6)-(Data!O6+Data!Q6)) | H7: =IFERROR(((Data!O6+Data!Q6)-((Data!N6+Data!P6)-(Data!O6+Data!Q6)))/((Data!N6+Data!P6)-(Data!O6+Data!Q6)),0)
B9: Detalhamento por promocode — dados do CSV (28/05)
B10: Promocode | C10: Campanha | D10: Ativações | E10: % novos | F10: Corridas | G10: Aluguéis PB | H10: GMV (R$) | I10: Cash (R$) | J10: Bônus (R$) | K10: ROI | L10: Util. orçamento
B11: =Data!A3 | C11: =Data!B3 | D11: =Data!G3 | E11: =IFERROR(Data!H3/Data!G3,0) | F11: =Data!J3 | G11: =Data!K3 | H11: =Data!N3+Data!P3 | I11: =Data!O3+Data!Q3 | J11: =(Data!N3+Data!P3)-(Data!O3+Data!Q3) | K11: =IFERROR((I11-J11)/J11,0) | L11: =IFERROR(J11/Data!R3,0)
B12: =Data!A4 | C12: =Data!B4 | D12: =Data!G4 | E12: =IFERROR(Data!H4/Data!G4,0) | F12: =Data!J4 | G12: =Data!K4 | H12: =Data!N4+Data!P4 | I12: =Data!O4+Data!Q4 | J12: =(Data!N4+Data!P4)-(Data!O4+Data!Q4) | K12: =IFERROR((I12-J12)/J12,0) | L12: =IFERROR(J12/Data!R4,0)
B13: =Data!A5 | C13: =Data!B5 | D13: =Data!G5 | E13: =IFERROR(Data!H5/Data!G5,0) | F13: =Data!J5 | G13: =Data!K5 | H13: =Data!N5+Data!P5 | I13: =Data!O5+Data!Q5 | J13: =(Data!N5+Data!P5)-(Data!O5+Data!Q5) | K13: =IFERROR((I13-J13)/J13,0) | L13: =IFERROR(J13/Data!R5,0)
B14: TOTAL | D14: =SUM(D11:D13) | E14: =IFERROR(SUM(Data!H3:H5)/SUM(Data!G3:G5),0) | F14: =SUM(F11:F13) | G14: =SUM(G11:G13) | H14: =SUM(H11:H13) | I14: =SUM(I11:I13) | J14: =SUM(J11:J13) | K14: =IFERROR((I14-J14)/J14,0) | L14: =IFERROR(SUM(J11:J13)/SUM(Data!R3:R5),0)
B17: 📦 KPIs FUTUROS — aguardando dados dos analistas
B18: CR1: cliques → ativações | C18: CR2: ativações → 1ª corrida | D18: LTV / cohort 30/60/90 dias | E18: CAC vs canais alternativos | F18: Custo de placement (parceiro) | G18: Distribuição geográfica | H18: Dinâmica W/W
B19: — | C19: — | D19: — | E19: — | F19: — | G19: — | H19: —
B20: Pedido por Ilya (07.05) | C20: Próximo passo do funil | D20: Resolve gap CSV vs Excel (lifetime) | E20: Hipótese de Ruslan | F20: Não incluído no custo total | G20: Hipótese de Ruslan | H20: Pedido por Ilya
B61: Insights & ações sugeridas (CSV 28/05)
B62: 🔥 ONDEIRBC1 (блоггер) — campeão: ROI ~1.218%, 414 corridas, R$ 3.671 Cash. Util. orçamento 4.5%. Replicar formato com outros blogueiros.
B63: 🔥 NIX (instagram) — ROI ~1.010%, 187 corridas, R$ 1.705 Cash. Util. orçamento 6.15%. Mídia paga funciona — considerar escala.
B64: ⚠️ HUBEES — 26 corridas, R$ 355 Cash. ROI 432% direto, mas Excel mostra 446 corridas lifetime (efeito halo). Validar com analistas qual é a métrica «verdadeira».
B65: 📊 Gap CSV (26 corridas HUBEES) vs Excel (446) NÃO é por defasagem de 4 dias — é diferença de escopo: CSV = janela de campanha; Excel = lifetime cohort. Vide card «LTV 30/60/90» em Pending.
B66: 📈 % de novos clientes (CSV): HUBEES 97%, NIX 96%, ONDEIRBC1 99%. Praticamente todos ativadores são novos — promo cumpre função de captação.

Sheet Cartões Pendentes
B2: Cartões pendentes — perguntas de Ilya & hipóteses de Ruslan que precisam de dados dos analistas
A4: # | B4: Cartão | C4: Pergunta original | D4: Quem pediu | E4: Por que importa | F4: O que precisamos dos analistas | G4: Status / ETA
A5: 1 | B5: Funil clicks → ativações (CR1) | C5: «Переходы по ссылкам, в штуках и деньгах» | D5: Ilya (07.05.2026, 15:11) | E5: Sem cliques não fechamos o funil. CR1 mostra eficiência da landing/canal antes da ativação. | F5: Кол-во кликов по UTM каждого промокода + источник (Instagram/email/banner partner). | G5: 🔴 Aguardando — pedir aos partners + Sirius BI
A6: 2 | B6: Funil ativações → 1ª corrida (CR2) | C6: Continuação lógica do funil | D6: Ruslan (hipótese) | E6: CSV já tem «Кол-во первых поездок» (8/27/105). Falta visualização cohort + tempo até 1ª corrida. | F6: Dias entre ativação e 1ª corrida + % de ativados que viraram corrida (cohort). | G6: 🟡 Parcial — dados existem, falta apresentação
A7: 3 | B7: LTV / retention 30/60/90 dias | C7: Resolve discrepância CSV 26 vs Excel 446 corridas (HUBEES) | D7: Ruslan (hipótese halo) | E7: CSV mede só janela de campanha. Para ROI completo, precisamos saber o que os usuários fazem 30/60/90 dias DEPOIS. | F7: Cohort de usuários ativados, GMV Cash mês a mês durante 90 dias após ativação. | G7: 🔴 Aguardando — Sirius BI cohort report
A8: 4 | B8: CAC: promo vs. outros canais | C8: «Quanto custaria atrair mesmo usuário sem promo?» | D8: Ruslan (hipótese) | E8: Sem benchmark não conseguimos dizer se R$ 1.7/ativação é caro ou barato. | F8: Custo de aquisição por canal (Meta ads, Google ads, ASO, referral) e CAC blended de 2026. | G8: 🟡 Pedir ao marketing
A9: 5 | B9: Custo de placement por parceiro | C9: Custo total = bônus + pagamento ao parceiro | D9: Ruslan (hipótese) | E9: Hoje só medimos bônus (subsídio). Pagamento ao blogueiro/Hubees/Instagram NÃO está incluído — ROI real pode ser bem menor. | F9: Tabela com R$ pago a cada parceiro por campanha (fee fixo, % share, custo de criativo). | G9: 🟡 Pedir ao financeiro
A10: 6 | B10: Distribuição geográfica das ativações | C10: Onde estão os usuários ativados? | D10: Ruslan (hipótese) | E10: Promocode Onde Ir BC deveria ativar em SC. Se ativações vêm de SP, há mismatch parceiro vs. região. | F10: Ativações por cidade × promocode. | G10: 🟡 Pedir Sirius BI
A11: 7 | B11: Dinâmica W/W (semana a semana) | C11: «Обновление раз в неделю» | D11: Ilya (07.05.2026, 15:04) | E11: Hoje temos snapshot acumulado. Dinâmica W/W mostra se a campanha está «morrendo» ou crescendo. | F11: Snapshot semanal automático (toda segunda-feira) — começamos coletando manualmente. | G11: 🟢 Em andamento — primeira linha em Snapshots semanais
A12: 8 | B12: UTM/source de cada ativação | C12: De qual canal exato veio cada usuário? | D12: Ruslan (hipótese) | E12: Promocode pode ser divulgado via Instagram, email, push, banner — sem UTM não sabemos qual canal funciona. | F12: Coluna «utm_source» no relatório de ativações. | G12: 🔴 Aguardando — pedir Sirius BI
A13: 9 | B13: Qualidade das ativações (fraud-check) | C13: Quantas ativações são reais vs. abuso? | D13: Ruslan (hipótese) | E13: ONDEIRBC1: 162 ativações em 4 meses por «blogueiro» com 300 códigos. Possível farm de contas / abuso. | F13: Flags de fraud do Sirius + cross-check device-id, IP, padrão de uso suspeito. | G13: 🟡 Pedir ao time anti-fraud
A14: 10 | B14: Comparação com não-cohort (controle) | C14: Quanto desses usuários teriam vindo de qualquer forma? | D14: Ruslan (hipótese) | E14: Sem grupo de controle, atribuímos 100% das corridas ao promo, mas parte viria sem ele. | F14: Estimativa de baseline (% de ativações que ocorreriam organicamente). | G14: 🟢 Nice to have

Sheet Metodologia
B2: Metodologia, fontes e regra de prioridade
B3: Regra: CSV (mais recente, 28/05) é primária. Excel (24/05) é usado como referência. Em divergências não-críticas, prevalece CSV. Divergências críticas são marcadas em Cartões Pendentes.
B5: Métrica | C5: Fonte primária | D5: Fonte referência | E5: Observação
B6: Ativações | C6: CSV (28/05) | D6: Excel (24/05) | E6: Discrepância pequena (HUBEES 29/29, NIX 108/108, ONDEIRBC1 164 vs 162). CSV mais recente.
B7: Novos clientes | C7: CSV | D7: Excel | E7: Definições diferentes: CSV «новый клиент» = cliente recente; Excel «привлечённый» = first contact. CSV usado por padrão.
B8: Corridas | C8: CSV (janela de campanha) | D8: Excel (lifetime cohort) | E8: DIVERGÊNCIA CRÍTICA: HUBEES 26 vs 446 — diferença metodológica, NÃO defasagem temporal. Vide card LTV em Pending.
B9: Aluguéis PB | C9: CSV | D9: Excel | E9: Diferença significativa (HUBEES 3 vs 26). Mesma causa: janela vs lifetime.
B10: GMV total / Cash | C10: CSV | D10: — | E10: Apenas no CSV. Valores reais por promocode.
B11: Bônus | C11: CSV: GMV − GMV Cash | D11: — | E11: Bônus efetivamente usado. NÃO inclui pagamento ao parceiro (vide card 'Placement').
B12: Orçamento máx. | C12: CSV | D12: — | E12: Limite teórico. HUBEES tem R$ 250k budget — usado 0.03%.
B13: Códigos emitidos | C13: CSV | D13: — | E13: Pool total de códigos disponibilizados.
B14: Data 1ª ativação | C14: Excel (referência) | D14: CSV (período de campanha) | E14: Excel registra a primeira ativação histórica. CSV mostra apenas a janela ativa.

Sheet Data
F1: CSV: 20260528_164649.csv | G1: CSV | H1: CSV | I1: CSV | J1: CSV | K1: CSV | L1: CSV | M1: CSV | N1: CSV | O1: CSV | P1: CSV | Q1: CSV | R1: CSV | S1: Excel: pb_sc_promocodes_24.05.xlsx (ref) | T1: Excel ref | U1: Excel ref
A2: Promocode | B2: Campanha (CSV) | C2: Parceiro | D2: Período início (CSV) | E2: Período fim (CSV) | F2: Códigos emitidos | G2: Ativações | H2: Ativações novos clientes | I2: Primeiras corridas (1ª trip) | J2: Corridas | K2: Aluguéis PB | L2: GMV 1ª (R$) | M2: GMV Cash 1ª (R$) | N2: GMV total (R$) | O2: GMV Cash (R$) | P2: GMV PB (R$) | Q2: GMV Cash PB (R$) | R2: Orçamento máx. (R$) | S2: Excel: Corridas lifetime | T2: Excel: PB lifetime | U2: Excel: 1ª ativação
A3: HUBEES | B3: HUBEES | C3: Hubees | D3: 46056 | E3: 46088 | F3: 5000 | G3: 29 | H3: 28 | I3: 8 | J3: 26 | K3: 3 | L3: 80.08 | M3: 355.34 | N3: 384.09 | O3: 355.34 | P3: 38 | Q3: 0 | R3: 250000 | S3: 446 | T3: 26 | U3: 46008
A4: NIX | B4: Nix (instagram) | C4: NIX | D4: 46130 | E4: 46190 | F4: 500 | G4: 108 | H4: 104 | I4: 27 | J4: 187 | K4: 2 | L4: 359.5 | M4: 1695.37 | N4: 1849.07 | O4: 1695.37 | P4: 10 | Q4: 10 | R4: 2500 | S4: 456 | T4: 17 | U4: 46130
A5: ONDEIRBC1 | B5: блоггер | C5: Onde Ir BC | D5: 46056 | E5: 46388 | F5: 300 | G5: 164 | H5: 162 | I5: 105 | J5: 414 | K5: 3 | L5: 1470.35 | M5: 3671.53 | N5: 3954.97 | O5: 3671.53 | P5: 62 | Q5: 62 | R5: 6300 | S5: 343 | T5: 2 | U5: 46063
A6: TOTAL | F6: =SUM(F3:F5) | G6: =SUM(G3:G5) | H6: =SUM(H3:H5) | I6: =SUM(I3:I5) | J6: =SUM(J3:J5) | K6: =SUM(K3:K5) | L6: =SUM(L3:L5) | M6: =SUM(M3:M5) | ... T6: =SUM(T3:T5)

Sheet Snapshots semanais
A1: Data snapshot | B1: Promocode | C1: Ativações | D1: Corridas | E1: Aluguéis PB | F1: GMV (R$) | G1: Cash (R$) | H1: Bônus (R$) | I1: ROI | J1: Comentário
A2: 46170 | B2: HUBEES | C2: 29 | D2: 26 | E2: 3 | F2: 422.09 | G2: 355.34 | H2: 66.75 | I2: =IFERROR((G2-H2)/H2,0) | J2: Linha de base — CSV de 28/05 como primária
A3: 46170 | B3: NIX | C3: 108 | D3: 187 | E3: 2 | F3: 1859.07 | G3: 1705.37 | H3: 153.7 | I3: =IFERROR((G3-H3)/H3,0) | J3: Linha de base — CSV de 28/05 como primária
A4: 46170 | B4: ONDEIRBC1 | C4: 164 | D4: 414 | E4: 3 | F4: 4016.97 | G4: 3733.53 | H4: 283.44 | I4: =IFERROR((G4-H4)/H4,0) | J4: Linha de base — CSV de 28/05 como primária
